LICENSE
README.md
setup.py
lib_upgrade/MANIFEST.in
lib_upgrade/__init__.py
lib_upgrade/lib_upgrade.py
lib_upgrade.egg-info/PKG-INFO
lib_upgrade.egg-info/SOURCES.txt
lib_upgrade.egg-info/dependency_links.txt
lib_upgrade.egg-info/not-zip-safe
lib_upgrade.egg-info/top_level.txt