Metadata-Version: 2.1
Name: lib-upgrade
Version: 0.1
Summary: Package to help developers check and upgrade their libraries as they wish
Home-page: https://github.com/ramos-rr/lib_upgrade
Author: Rafael Ramos da Silva
Author-email: ramos-rr@outlook.com
License: BSD
Classifier: Development Status :: 2 - Pre-Alpha
Classifier: Environment :: Console
Classifier: Intended Audience :: Developers
Classifier: License :: OSI Approved :: BSD License
Classifier: Operating System :: OS Independent
Classifier: Programming Language :: Python :: 3.10
Classifier: Framework :: Pytest
License-File: LICENSE
